{"description": "", "members": [{"position": "1", "first_name": "", "last_name": "van Tuyll van Serooskerken", "place": "Haarlem", "gender": "m"}, {"position": "2", "first_name": "", "last_name": "van Endhoven", "place": "Well", "gender": "m"}, {"position": "3", "first_name": "", "last_name": "van Dartel", "place": "'s-Hertogenbosch", "gender": "v"}, {"position": "4", "first_name": "", "last_name": "Witteveen", "place": "Amsterdam", "gender": "v"}, {"position": "5", "first_name": "", "last_name": "van Eenennaam", "place": "Hello\u00b0", "gender": "m"}, {"position": "6", "first_name": "", "last_name": "de Boevere", "place": "Breskens", "gender": "v"}, {"position": "7", "first_name": "", "last_name": "van Teeffelen", "place": "Rotterdam", "gender": "m"}, {"position": "8", "first_name": "", "last_name": "van Ittersum", "place": "Tuk", "gender": "m"}, {"position": "9", "first_name": "", "last_name": "ten Hoor", "place": "Leidschendam", "gender": "m"}, {"position": "10", "first_name": "", "last_name": "Berends", "place": "Utrecht", "gender": "m"}, {"position": "11", "first_name": "", "last_name": "Cohen Tervaert", "place": "Bosch en Duin", "gender": "m"}, {"position": "12", "first_name": "", "last_name": "Ankersmit", "place": "Glimmen", "gender": "m"}], "title": "Liberaal Democratische Partij"}