{
  "title": "Lijst 3 CDA",
  "description": "",
  "candidates": [
    {
      "position": 1,
      "full_name": "H.G. Jumelet",
      "place": "Erica",
      "gender": "m",
      "last_name": "Jumelet",
      "first_name": "Henk"
    },
    {
      "position": 2,
      "full_name": "D.B. Dijkstra",
      "place": "Diever",
      "gender": "m",
      "last_name": "Dijkstra",
      "first_name": "Dick"
    },
    {
      "position": 3,
      "full_name": "R. Wollerich-Veldman",
      "place": "Nieuw-Buinen",
      "gender": "v",
      "last_name": "Wollerich-Veldman",
      "first_name": "Riëtte"
    },
    {
      "position": 4,
      "full_name": "S.J. Vegter",
      "place": "Assen",
      "gender": "m",
      "last_name": "Vegter",
      "first_name": "Siemen"
    },
    {
      "position": 5,
      "full_name": "H. Reinders",
      "place": "Nieuweroord",
      "gender": "m",
      "last_name": "Reinders",
      "first_name": "Henk"
    },
    {
      "position": 6,
      "full_name": "K. Neutel",
      "place": "Nijeveen",
      "gender": "m",
      "last_name": "Neutel",
      "first_name": "Klaas"
    },
    {
      "position": 7,
      "full_name": "B. van Dekken",
      "place": "Zuidwolde",
      "gender": "m",
      "last_name": "van Dekken",
      "first_name": "Bart"
    },
    {
      "position": 8,
      "full_name": "L.M. Kremers",
      "place": "Zuidlaren",
      "gender": "m",
      "last_name": "Kremers",
      "first_name": "Martin"
    },
    {
      "position": 9,
      "full_name": "G. Seinen",
      "place": "Emmen",
      "gender": "v",
      "last_name": "Seinen",
      "first_name": "Greet"
    },
    {
      "position": 10,
      "full_name": "M. Louissen",
      "place": "Westerbork",
      "gender": "m",
      "last_name": "Louissen",
      "first_name": "Marinus"
    },
    {
      "position": 11,
      "full_name": "R. Wilting",
      "place": "Erm",
      "gender": "m",
      "last_name": "Wilting",
      "first_name": "Ruud"
    },
    {
      "position": 12,
      "full_name": "J.A.M. Mentink",
      "place": "Gieterveen",
      "gender": "m",
      "last_name": "Mentink",
      "first_name": "Hans"
    },
    {
      "position": 13,
      "full_name": "K.H. Knot",
      "place": "Zuidlaren",
      "gender": "m",
      "last_name": "Knot",
      "first_name": "Klaas"
    },
    {
      "position": 14,
      "full_name": "M.J.M. Smidt-Beudeker",
      "place": "Dieverbrug",
      "gender": "v",
      "last_name": "Smidt-Beudeker",
      "first_name": "Monique"
    },
    {
      "position": 15,
      "full_name": "J.E.M.G. van Dalen",
      "place": "Oosterhesselen",
      "gender": "v",
      "last_name": "van Dalen",
      "first_name": "Ilse"
    },
    {
      "position": 16,
      "full_name": "H. van de Pol",
      "place": "Assen",
      "gender": "m",
      "last_name": "van de Pol",
      "first_name": "Harry"
    },
    {
      "position": 17,
      "full_name": "L. Hummel",
      "place": "Hollandscheveld",
      "gender": "m",
      "last_name": "Hummel",
      "first_name": "Lucas"
    },
    {
      "position": 18,
      "full_name": "E.A. Wiersma",
      "place": "Zweeloo",
      "gender": "m",
      "last_name": "Wiersma",
      "first_name": "Epke"
    },
    {
      "position": 19,
      "full_name": "H. Linstra",
      "place": "Assen",
      "gender": "m",
      "last_name": "Linstra",
      "first_name": "Henk"
    },
    {
      "position": 20,
      "full_name": "J. Hospers",
      "place": "Nieuwlande",
      "gender": "m",
      "last_name": "Hospers",
      "first_name": "Jan"
    },
    {
      "position": 21,
      "full_name": "J.H. Lammers",
      "place": "Zuidwolde",
      "gender": "m",
      "last_name": "Lammers",
      "first_name": "Henk"
    },
    {
      "position": 22,
      "full_name": "B.D. Wilms",
      "place": "Schoonebeek",
      "gender": "m",
      "last_name": "Wilms",
      "first_name": "Bouke Durk"
    },
    {
      "position": 23,
      "full_name": "H. Schoonheim-Lunenborg",
      "place": "Hoogeveen",
      "gender": "v",
      "last_name": "Schoonheim-Lunenborg",
      "first_name": "Hennita"
    },
    {
      "position": 24,
      "full_name": "E.E. Scheepstra",
      "place": "Een",
      "gender": "v",
      "last_name": "Scheepstra",
      "first_name": "Emmaly"
    },
    {
      "position": 25,
      "full_name": "K. Drost",
      "place": "Zuidwolde",
      "gender": "m",
      "last_name": "Drost",
      "first_name": "Koop"
    },
    {
      "position": 26,
      "full_name": "H.A.M. van Hooft",
      "place": "Assen",
      "gender": "m",
      "last_name": "van Hooft",
      "first_name": "Henk"
    },
    {
      "position": 27,
      "full_name": "C.J.M. Ruhe",
      "place": "Erica",
      "gender": "m",
      "last_name": "Ruhe",
      "first_name": "Cees"
    },
    {
      "position": 28,
      "full_name": "E. Mulder",
      "place": "Havelte",
      "gender": "m",
      "last_name": "Mulder",
      "first_name": "Ernst"
    },
    {
      "position": 29,
      "full_name": "W. Rumph",
      "place": "Ruinerwold",
      "gender": "m",
      "last_name": "Rumph",
      "first_name": "Willem"
    },
    {
      "position": 30,
      "full_name": "B. Janssen",
      "place": "Een",
      "gender": "m",
      "last_name": "Janssen",
      "first_name": "Berend"
    },
    {
      "position": 31,
      "full_name": "J. Top",
      "place": "Ees",
      "gender": "m",
      "last_name": "Top",
      "first_name": "Jan"
    },
    {
      "position": 32,
      "full_name": "F.M. Hartmann",
      "place": "Emmen",
      "gender": "v",
      "last_name": "Hartmann",
      "first_name": "Marie"
    },
    {
      "position": 33,
      "full_name": "W.R. van Noord-Hasper",
      "place": "Dwingeloo",
      "gender": "v",
      "last_name": "van Noord-Hasper",
      "first_name": "Bien"
    },
    {
      "position": 34,
      "full_name": "J. Beijering",
      "place": "Hoogeveen",
      "gender": "m",
      "last_name": "Beijering",
      "first_name": "Johan"
    },
    {
      "position": 35,
      "full_name": "H. Bouwhuis",
      "place": "Westerbork",
      "gender": "m",
      "last_name": "Bouwhuis",
      "first_name": "Henk"
    },
    {
      "position": 36,
      "full_name": "T. Breimer",
      "place": "Assen",
      "gender": "m",
      "last_name": "Breimer",
      "first_name": "Tibbe"
    }
  ]
}
