{
  "title": "Lijst 7 Stichting Veilig Vitaal Waterbeheer",
  "description": "Gecombineerd met DWLK & Schieland: Helder als water",
  "candidates": [
    {
      "position": 1,
      "full_name": "J.A. Schep",
      "place": "Bergambacht",
      "gender": "",
      "last_name": "Schep",
      "first_name": "Jaap"
    },
    {
      "position": 2,
      "full_name": "J.C. van der Wel",
      "place": "Zevenhuizen",
      "gender": "",
      "last_name": "van der Wel",
      "first_name": "Jan"
    },
    {
      "position": 3,
      "full_name": "A. Vonk Noordegraaf",
      "place": "Stolwijk",
      "gender": "",
      "last_name": "Vonk Noordegraaf",
      "first_name": "Ton"
    },
    {
      "position": 4,
      "full_name": "T.C.G. Koolhaas - van den Ban",
      "place": "Moerkapelle",
      "gender": "",
      "last_name": "Koolhaas - van den Ban",
      "first_name": "Cora"
    },
    {
      "position": 5,
      "full_name": "L. Kool",
      "place": "Stolwijk",
      "gender": "",
      "last_name": "Kool",
      "first_name": "Leo"
    },
    {
      "position": 6,
      "full_name": "J. Hoogendoorn",
      "place": "Nieuwerkerk aan den IJssel",
      "gender": "",
      "last_name": "Hoogendoorn",
      "first_name": "Koos"
    },
    {
      "position": 7,
      "full_name": "P. de Vos - van den Berg",
      "place": "Krimpen aan de Lek",
      "gender": "",
      "last_name": "de Vos - van den Berg",
      "first_name": "Petra"
    },
    {
      "position": 8,
      "full_name": "J.H. van den Hoek",
      "place": "Zevenhuizen",
      "gender": "",
      "last_name": "van den Hoek",
      "first_name": "Han"
    },
    {
      "position": 9,
      "full_name": "A. Vonk Noordegraaf",
      "place": "Ouderkerk aan den IJssel",
      "gender": "",
      "last_name": "Vonk Noordegraaf",
      "first_name": "Antonie"
    },
    {
      "position": 10,
      "full_name": "J.P. Stolk",
      "place": "Waddinxveen",
      "gender": "",
      "last_name": "Stolk",
      "first_name": "Jan Pieter"
    },
    {
      "position": 11,
      "full_name": "J. Verburg",
      "place": "Stolwijk",
      "gender": "",
      "last_name": "Verburg",
      "first_name": "Jan"
    },
    {
      "position": 12,
      "full_name": "C.W. Villerius - van Rijn",
      "place": "Moerkapelle",
      "gender": "",
      "last_name": "Villerius - van Rijn",
      "first_name": "Kitty"
    },
    {
      "position": 13,
      "full_name": "W.P. Boer",
      "place": "Stolwijk",
      "gender": "",
      "last_name": "Boer",
      "first_name": "Pim"
    },
    {
      "position": 14,
      "full_name": "D.H. Mostert",
      "place": "Nieuwerkerk aan den IJssel",
      "gender": "",
      "last_name": "Mostert",
      "first_name": "David"
    },
    {
      "position": 15,
      "full_name": "P.C. Verhagen",
      "place": "Stolwijk",
      "gender": "",
      "last_name": "Verhagen",
      "first_name": "Cees"
    },
    {
      "position": 16,
      "full_name": "M. de Vries",
      "place": "Stolwijk",
      "gender": "",
      "last_name": "de Vries",
      "first_name": "Marinus"
    },
    {
      "position": 17,
      "full_name": "L. Broere",
      "place": "Lekkerkerk",
      "gender": "",
      "last_name": "Broere",
      "first_name": "Leonard"
    },
    {
      "position": 18,
      "full_name": "M.J. Verkaik",
      "place": "Ouderkerk aan den IJssel",
      "gender": "",
      "last_name": "Verkaik",
      "first_name": "Mart Jan"
    },
    {
      "position": 19,
      "full_name": "D. de Jong",
      "place": "Stolwijk",
      "gender": "",
      "last_name": "de Jong",
      "first_name": "David"
    },
    {
      "position": 20,
      "full_name": "S. de Bruijn",
      "place": "Berkenwoude",
      "gender": "",
      "last_name": "de Bruijn",
      "first_name": "Stoffel"
    },
    {
      "position": 21,
      "full_name": "P.G. Blanken",
      "place": "Gouderak",
      "gender": "",
      "last_name": "Blanken",
      "first_name": "Piet"
    },
    {
      "position": 22,
      "full_name": "A. Scheer",
      "place": "Lekkerkerk",
      "gender": "",
      "last_name": "Scheer",
      "first_name": "Ad"
    }
  ]
}
