{
  "title": "Lijst 6 Staatkundig Gereformeerde Partij (SGP)",
  "description": "Gecombineerd met CDA en ChristenUnie",
  "candidates": [
    {
      "position": 1,
      "full_name": "W. de Jong",
      "place": "Hendrik-Ido-Ambacht",
      "gender": "m",
      "last_name": "de Jong",
      "first_name": "Wim"
    },
    {
      "position": 2,
      "full_name": "J. van Helden",
      "place": "'s-Gravendeel",
      "gender": "m",
      "last_name": "van Helden",
      "first_name": "Sjaak"
    },
    {
      "position": 3,
      "full_name": "A.P.J. van den Berg",
      "place": "Ridderkerk",
      "gender": "m",
      "last_name": "van den Berg",
      "first_name": "Albert-Jan"
    },
    {
      "position": 4,
      "full_name": "P.C. Grinwis",
      "place": "Ouddorp",
      "gender": "m",
      "last_name": "Grinwis",
      "first_name": "Peter"
    },
    {
      "position": 5,
      "full_name": "T.A. Stoop",
      "place": "Hendrik-Ido-Ambacht",
      "gender": "m",
      "last_name": "Stoop",
      "first_name": "Teunis"
    },
    {
      "position": 6,
      "full_name": "A.J. Herweijer",
      "place": "Klaaswaal",
      "gender": "m",
      "last_name": "Herweijer",
      "first_name": "Ad"
    },
    {
      "position": 7,
      "full_name": "A.J. Kardux",
      "place": "Dirksland",
      "gender": "m",
      "last_name": "Kardux",
      "first_name": "Aren-Jan"
    },
    {
      "position": 8,
      "full_name": "C.A. van der Duijn Schouten",
      "place": "Ridderkerk",
      "gender": "m",
      "last_name": "van der Duijn Schouten",
      "first_name": "Kees"
    },
    {
      "position": 9,
      "full_name": "J.S. Breedveld",
      "place": "Barendrecht",
      "gender": "m",
      "last_name": "Breedveld",
      "first_name": "John"
    },
    {
      "position": 10,
      "full_name": "P. Kranendonk",
      "place": "Ridderkerk",
      "gender": "m",
      "last_name": "Kranendonk",
      "first_name": "Peter"
    },
    {
      "position": 11,
      "full_name": "W. Boonzaaijer",
      "place": "Rotterdam",
      "gender": "m",
      "last_name": "Boonzaaijer",
      "first_name": "Wouter"
    },
    {
      "position": 12,
      "full_name": "A. Hoogesteger",
      "place": "Dordrecht",
      "gender": "m",
      "last_name": "Hoogesteger",
      "first_name": "Ab"
    },
    {
      "position": 13,
      "full_name": "G. Slootweg",
      "place": "Middelharnis",
      "gender": "m",
      "last_name": "Slootweg",
      "first_name": "Gert"
    },
    {
      "position": 14,
      "full_name": "B. Staat",
      "place": "Dordrecht",
      "gender": "m",
      "last_name": "Staat",
      "first_name": "Bert"
    },
    {
      "position": 15,
      "full_name": "A.T. van der Wulp",
      "place": "'s-Gravendeel",
      "gender": "m",
      "last_name": "van der Wulp",
      "first_name": "Anthony"
    },
    {
      "position": 16,
      "full_name": "A.G.M. Born",
      "place": "Sommelsdijk",
      "gender": "m",
      "last_name": "Born",
      "first_name": "Marco"
    },
    {
      "position": 17,
      "full_name": "J.K. Matze",
      "place": "Nieuw-Beijerland",
      "gender": "m",
      "last_name": "Matze",
      "first_name": "Johan"
    },
    {
      "position": 18,
      "full_name": "A. Houweling",
      "place": "Oude-Tonge",
      "gender": "m",
      "last_name": "Houweling",
      "first_name": "Adri"
    },
    {
      "position": 19,
      "full_name": "A. van der Linden",
      "place": "Nieuw-Beijerland",
      "gender": "m",
      "last_name": "van der Linden",
      "first_name": "Arie"
    }
  ]
}
